Workbook

Sheet README
A1: LibreDAB — Planning Pack (block diagram, BOM, size & risk)
A2: Open-source GaN, 1 MHz Dual Active Bridge — Sodium-Ion battery <-> 400 V DC link, 800 W
A4: Status | B4: Planning stage. Figures are first-pass estimates to be confirmed in detailed design + prototype.
A5: Prepared | B5: Initial pass, June 2026
A6: Locked decisions | B6: Full-bridge both sides; SPIN as plug-in controller; series L from transformer leakage; cooling sized from thermals.
A8: Confidence legend | B8: H = high (datasheet/quote), M = medium (engineering estimate), L = low (rough / needs prototype)
A9: Colour legend | B9: Blue cells = inputs you can change. Black = calculated/text. Yellow = key assumption.
A10: FX assumption | B10: GBP per USD used for converting USD-quoted parts (see Cost_Summary, change in one place).
A12: Sheets
A13: Design_Calcs | B13: DAB operating points, required series inductance, transformer flux density & leakage feasibility.
A14: Loss_Thermal | B14: Loss budget at nominal and worst-case corner; efficiency; cooling recommendation.
A15: BOM | B15: Line-by-line bill of materials with sources (LCSC / UK-custom / off-LCSC), costs and references.
A16: Cost_Summary | B16: Roll-up by category, per-board total and low/high range.
A17: Size_Estimate | B17: Area budget against the 70 x 280 mm single-sided board; Z-height note.
A18: Risk_Register | B18: Ranked risks with likelihood x impact and mitigations.
A19: References | B19: All sources with URLs (every checkable figure is traceable here).
A21: IMPORTANT | B21: GaN power devices (LMG2100R026, LMG2652) are NOT in the LCSC catalogue. They are off-LCSC lines
B22: (Mouser/DigiKey/TI) - now an all-TI power stage (single vendor). All-LCSC HV fallback (Tokmas CID12N65D x4 + drivers) noted in BOM.

Sheet Design_Calcs
A1: DAB Design Calculations (single-phase-shift model)
A2: Topology assumption: full bridge both sides, battery = primary (1T), DC link = secondary (11T)
A4: Inputs (blue = change)
A5: Battery nominal voltage | B5: 42 | C5: V
A6: Battery minimum voltage | B6: 23.8 | C6: V
A7: Battery maximum voltage | B7: 58.8 | C7: V
A8: DC link voltage | B8: 400 | C8: V
A9: Rated power | B9: 800 | C9: W
A10: Switching frequency | B10: 1000000 | C10: Hz
A11: Turns ratio n = Ns/Np | B11: 11 | C11: -
A12: Primary turns Np | B12: 1 | C12: -
A13: Core A_L (assembled pair) | B13: 3.7e-06 | C13: H
A14: Core effective area Ae | B14: 0.000146 | C14: m^2
A15: Design phase shift (nominal) | B15: 50 | C15: deg
A16: Assumed efficiency (for current calc) | B16: 0.95 | C16: -
A17: Primary RMS factor (x I_dc, rough) | B17: 1.2 | C17: -
A19: Calculations
A20: Secondary turns Ns | B20: =$B$11*$B$12 -> 11 | C20: -
A21: Reflected link voltage to primary (Vlink/n) | B21: =$B$8/$B$11 -> 36.363636 | C21: V
A22: Battery current at nominal | B22: =$B$9/$B$5 -> 19.047619 | C22: A
A23: Battery current at min V (incl. eff.) | B23: =$B$9/($B$16*$B$6) -> 35.382574 | C23: A
A24: Phase shift (radians) | B24: =$B$15*PI()/180 -> 0.87266463 | C24: rad
A25: Phase shape factor φ(1-φ/π) | B25: =B24*(1-B24/PI()) -> 0.63025779 | C25: -
A26: REQUIRED series inductance, referred to primary | B26: =$B$5*B21*B25/(2*PI()*$B$10*$B$9) -> 1.9149832e-07 | C26: H
A27: = required series inductance (primary) | B27: =B26*1000000000 -> 191.49832 | C27: nH
A28: = required series inductance (secondary) | B28: =B26*$B$11^2*1000000 -> 23.171296 | C28: uH
A29: Magnetizing inductance (primary) | B29: =$B$13*$B$12^2 -> 3.7e-06 | C29: H
A30: Required leakage as % of magnetizing | B30: =B26/B29 -> 0.051756302 | C30: %
A31: Peak flux density (secondary, square-wave approx) | B31: =$B$8/(4*$B$10*B20*$B$14) -> 0.062266501 | C31: T
A32: = peak flux density (secondary) | B32: =B31*1000 -> 62.266501 | C32: mT
A33: Peak flux density (primary, approx) | B33: =$B$5/(4*$B$10*$B$12*$B$14)*1000 -> 71.917808 | C33: mT
A34: Primary RMS current at nominal | B34: =$B$17*B22 -> 22.857143 | C34: A
A35: Primary RMS current at min-V corner | B35: =$B$17*B23 -> 42.459089 | C35: A
A36: Interpretation
A37: Required leakage (~5% of magnetizing) is HIGH for a tightly-coupled RM transformer (typical 1-3%).
A38: Achieving AND controlling this with a single-turn primary is the dominant magnetics risk (see Risk M-01).
A39: Flux density ~60-72 mT at 1 MHz in N49 is acceptable but core loss is non-trivial (see Loss_Thermal).
A40: Battery range 23.8-58.8 V is a 2.47:1 swing -> reflected 262-647 V vs fixed 400 V link; ZVS range and RMS
A41: currents vary strongly with state-of-charge. Adaptive modulation likely needed (Risk C-01).
A42: Required series L scales with design phase shift (blue input row 15); lower phase shift -> lower L needed.

Sheet Loss_Thermal
A1: Loss Budget & Thermal Recommendation
A2: Efficiency target >95% at NOMINAL (42 V, 800 W). Worst case = 23.8 V / full power.
A4: Block | B4: Loss @ nominal (W) | C4: Loss @ worst corner (W) | D4: Confidence | E4: Basis / source
A5: LV full bridge (2x LMG2100R026, 2.6 mΩ) | B5: 5 | C5: 11 | D5: M | E5: Lower Rds (2.6 mΩ) cuts conduction; 53 A rating eases low-V corner
A6: HV full bridge (2x LMG2652, 140 mΩ) | B6: 5 | C6: 7 | D6: M | E6: Low HV current; 650 V ZVS switching dominates at 1 MHz
A7: HF transformer (core + copper) | B7: 4 | C7: 6 | D7: M | E7: N49 ~60-72 mT @1 MHz; user est 2 W is optimistic
A8: Bias / gate drive / control | B8: 2 | C8: 3 | D8: M | E8: Gate charge x f, aux supply, sensing
A9: PCB / interconnect / connectors | B9: 2 | C9: 4 | D9: L | E9: I^2R in copper at 19-35 A on LV side
A10: TOTAL LOSS | B10: =SUM(B5:B9) -> 18 | C10: =SUM(C5:C9) -> 31
A11: Output power (W) | B11: 800
A12: Estimated efficiency | B12: =B11/(B11+B10) -> 0.97799511 | C12: =B11/(B11+C10) -> 0.96269555
A14: Cooling recommendation (sized from thermals)
A15: Worst-case ~40 W (low-SoC, full power) over a 70x280 mm (196 cm^2) single-sided board.
A16: Natural convection alone (~10-20 W at acceptable rise) is INSUFFICIENT at the worst corner.
A17: RECOMMENDED: conduction to a chassis/baseplate as the main heat path, plus a screw-mounted
A18: top-side heatsink bar over the LV stage (EPC23102 has an exposed-TOP cooling pad - ideal, removable).
A19: HV stage (LMG2652) is bottom-cooled: thermal vias to a bottom plane -> gap pad -> chassis.
A20: Provide footprint/headers for an optional small fan for continuous worst-corner operation.
A21: This satisfies the repairability rules: single-sided placement, screwed (not potted) heatsinks.

Sheet BOM
A1: Bill of Materials (per board, low-volume / prototype pricing)
A2: Sources: LCSC (PCBway-orderable) unless noted UK-custom or off-LCSC. Costs in GBP.
A4: # | B4: Block | C4: Function / Ref | D4: Part number | E4: Mfr | F4: Source | G4: Qty | H4: Unit £ | I4: Ext £ | J4: Quoted price (native) | K4: Datasheet / link | L4: Conf. | M4: Notes
A5: 1 | B5: LV bridge | C5: HS+LS GaN half-bridge x2 (full bridge) | D5: LMG2100R026 | E5: TI | F5: off-LCSC (Mouser/DigiKey) | G5: 2 | H5: 8 | I5: =G5*H5 -> 16 | J5: ~$8-13 low qty; in stock | K5: https://www.ti.com/product/LMG2100R026 | L5: M | M5: 93V cont/100V pulsed, 53A, 2.6 mOhm, top-cooled. All-TI w/ HV. NOT on LCSC
A6: 2 | B6: HV bridge | C6: HV GaN half-bridge x2 (full bridge) | D6: LMG2652RFBR | E6: TI | F6: off-LCSC (Mouser/DigiKey) | G6: 0 | H6: 6 | I6: =G6*H6 -> 0 | J6: ~$7-8; 12-wk lead | K6: https://www.ti.com/product/LMG2652 | L6: M | M6: Integrated driver+current sense; bottom-cooled; 12-wk lead
A7: 3 | B7: HV bridge (ALT) | C7: All-LCSC HV fallback: single switch x4 + drivers | D7: CID12N65D | E7: Tokmas | F7: LCSC C21547657 | G7: 4 | H7: 0.5 | I7: =G7*H7 -> 2 | J7: $0.6276 LCSC | K7: https://www.lcsc.com/product-detail/C21547657.html | L7: M | M7: Alternative path: needs 4 x modules instead of 2 x
A8: 4 | B8: Magnetics | C8: RM12 core set (N49) | D8: B65815E0000R049 | E8: TDK/EPCOS | F8: UK (Farnell/TME) - custom | G8: 1 | H8: 8 | I8: =G8*H8 -> 8 | J8: ~£6-12/pair | K8: https://uk.farnell.com/epcos/b65815e0000r049/transformer-core-rm-n49-57mm/dp/4167325 | L8: M | M8: A_L 3700 nH, Ae 146 mm^2, sold as pair
A9: 5 | B9: Magnetics | C9: RM12 coil former (bobbin) + clips | D9: RM12 bobbin/clip set | E9: TDK/EPCOS | F9: UK - custom | G9: 1 | H9: 4 | I9: =G9*H9 -> 4 | J9: ~£3-5 | K9: https://www.tdk-electronics.tdk.com/inf/80/db/fer/rm_12.pdf | L9: M | M9: Required to wind transformer
A10: 6 | B10: Magnetics | C10: Litz wire (primary heavy + secondary) | D10: Litz 12A & 3A | E10: RM Cybernetics | F10: UK - custom | G10: 1 | H10: 15 | I10: =G10*H10 -> 15 | J10: ~£10-25 | K10: https://www.rmcybernetics.com/ | L10: L | M10: Single-turn primary at ~40 A RMS may need paralleled bundles
A11: 7 | B11: Magnetics | C11: Transformer winding / assembly (custom labour) | D11: Custom wound RM12 | E11: UK winder | F11: UK - custom | G11: 1 | H11: 25 | I11: =G11*H11 -> 25 | J11: ~£15-50 | K11: https://www.rmcybernetics.com/ | L11: L | M11: Leakage must be tuned & measured; biggest cost uncertainty
A12: 8 | B12: HV cap | C12: DC-link bus capacitance (C0G/film, 500-630 V) | D12: ceramic/film array | E12: various | F12: LCSC | G12: 1 | H12: 8 | I12: =G12*H12 -> 8 | J12: allowance | K12: https://www.lcsc.com/ | L12: M | M12: High-freq bus decoupling near HV bridge
A13: 9 | B13: LV cap | C13: Battery-side bulk + decoupling (high ripple) | D13: ceramic + polymer | E13: various | F13: LCSC | G13: 1 | H13: 8 | I13: =G13*H13 -> 8 | J13: allowance | K13: https://www.lcsc.com/ | L13: M | M13: Ripple current rating critical at 1 MHz / 35 A
A14: 10 | B14: Sensing | C14: Battery current sense (shunt + isolated amp or Hall) | D14: e.g. TMCS/INA-class | E14: various | F14: LCSC | G14: 1 | H14: 5 | I14: =G14*H14 -> 5 | J14: allowance | K14: https://www.lcsc.com/ | L14: M | M14: HV current available from LMG2652 integrated sense
A15: 11 | B15: Sensing | C15: Voltage dividers + scaling buffer (both sides, 0-2.048 V) | D15: resistors + op-amp | E15: various | F15: LCSC | G15: 1 | H15: 3 | I15: =G15*H15 -> 3 | J15: allowance | K15: https://www.lcsc.com/ | L15: M | M15: Conditioned to SPIN ADC 0-2.048 V range
A16: 12 | B16: Bias | C16: Aux/isolated supply + LDOs (5 V / VDD rails) | D16: iso DC-DC + LDO | E16: various | F16: LCSC | G16: 1 | H16: 6 | I16: =G16*H16 -> 6 | J16: allowance | K16: https://www.lcsc.com/ | L16: M | M16: Powers GaN gate-driver bias on both domains
A17: 13 | B17: Interface | C17: Battery connector (35 A rated) | D17: screw terminal / high-current | E17: various | F17: LCSC | G17: 1 | H17: 4 | I17: =G17*H17 -> 4 | J17: allowance | K17: https://www.lcsc.com/ | L17: M | M17: Repairable, re-mountable per golden rules
A18: 14 | B18: Interface | C18: 400 V link connector | D18: >600 V rated | E18: various | F18: LCSC | G18: 1 | H18: 3 | I18: =G18*H18 -> 3 | J18: allowance | K18: https://www.lcsc.com/ | L18: M
A19: 15 | B19: Interface | C19: SPIN header (2.54 mm) | D19: pin header | E19: various | F19: LCSC | G19: 1 | H19: 2 | I19: =G19*H19 -> 2 | J19: allowance | K19: https://www.owntech.org/spin-2/ | L19: H | M19: PWM out + ADC in (0-2.048 V) + serial/analog ref
A20: 16 | B20: Interface | C20: Test points (all major nets) | D20: SMD test points | E20: various | F20: LCSC | G20: 1 | H20: 2 | I20: =G20*H20 -> 2 | J20: allowance | K20: https://www.lcsc.com/ | L20: H | M20: Golden rule: TPs on all major power & control nets
A21: 17 | B21: Indicator | C21: 'No Error' status LED + driver | D21: LED + transistor | E21: various | F21: LCSC | G21: 1 | H21: 1 | I21: =G21*H21 -> 1 | J21: allowance | K21: https://www.lcsc.com/ | L21: H | M21: Absence of indication = error
A22: 18 | B22: Passives | C22: Gate Rs, bootstrap caps, decouplers, dividers | D22: 0402/0603 passives | E22: various | F22: LCSC | G22: 1 | H22: 5 | I22: =G22*H22 -> 5 | J22: allowance | K22: https://www.lcsc.com/ | L22: M | M22: Min. part diversity per golden rules
A23: 19 | B23: Thermal | C23: Top-side heatsink (LV) + TIM + screws | D23: heatsink+pad | E23: various | F23: UK/LCSC | G23: 1 | H23: 6 | I23: =G23*H23 -> 6 | J23: ~£4-10 | K23: https://www.lcsc.com/ | L23: L | M23: Screw-mounted, removable
A24: 20 | B24: PCB | C24: 4-layer 2 oz, 70 x 280 mm (qty 5 amortised) | D24: custom PCB | E24: PCBway | F24: PCBway | G24: 1 | H24: 20 | I24: =G24*H24 -> 20 | J24: ~£12-35/board | K24: https://www.pcbway.com/orderonline.aspx | L24: L | M24: 2 oz copper + large area push cost up; use PCBway calculator
H25: PER-BOARD TOTAL | I25: =SUM(I5:I24) -> 143
B27: Note: ALT row (Tokmas) qty set to 0 so it is excluded from the total; switch quantities to swap the HV path.

Sheet Cost_Summary
A1: Cost Summary (per board)
A3: FX assumption: GBP per USD | B3: 0.79 | C3: (=1/1.27; used where parts quoted in USD)
A5: Category | B5: Cost £ | C5: Confidence | D5: Comment
A6: Semiconductors (GaN) | B6: =BOM!I5+BOM!I6 -> 16 | C6: M | D6: LMG2100R026 x2 + LMG2652 x2; all-TI, off-LCSC
A7: Magnetics (custom, UK) | B7: =SUM(BOM!I8:I11) -> 52 | C7: L | D7: Core+bobbin+litz+winding; dominant uncertainty
A8: Capacitors | B8: =SUM(BOM!I12:I13) -> 16 | C8: M | D8: HV bus + LV bulk/decoupling
A9: Sensing & control interface | B9: =SUM(BOM!I14:I21) -> 26 | C9: M | D9: Current/voltage sense, bias, connectors, TPs, LED
A10: Misc passives | B10: =BOM!I22 -> 5 | C10: M | D10: Gate Rs, bootstrap, dividers
A11: Thermal | B11: =BOM!I23 -> 6 | C11: L | D11: Heatsink + TIM
A12: PCB (PCBway) | B12: =BOM!I24 -> 20 | C12: L | D12: 4-layer 2 oz, 70x280 mm
A13: POINT-ESTIMATE TOTAL | B13: =SUM(B6:B12) -> 141
A15: Range factors (blue)
A16: Low factor | B16: 0.75
A17: High factor | B17: 1.55
A18: Estimated low (£) | B18: =B13*B16 -> 105.75
A19: Estimated high (£) | B19: =B13*B17 -> 218.55
A21: Overall cost confidence: M-L. Drivers of spread: custom transformer, low-qty GaN pricing, PCB area/copper.

Sheet Size_Estimate
A1: Size Estimate vs 70 x 280 mm target
A3: Board area available (single-sided) | B3: =70*280/100 -> 196 | C3: cm^2 (=196)
A5: Block | B5: Approx area (cm^2) | C5: Conf. | D5: Notes (footprint basis)
A6: LV full bridge + input caps | B6: 22 | C6: M | D6: 2x LMG2100R026 (7x4.5 mm) + decoupling + heavy-copper pour
A7: HV full bridge + bus caps | B7: 22 | C7: M | D7: 2x LMG2652 (6x8 mm) + 400 V bus caps
A8: HF transformer (RM12) | B8: 18 | C8: M | D8: Core ~37.6x29.8 mm + clearance; tallest part ~25 mm
A9: Sensing + bias + control interface | B9: 25 | C9: M | D9: Dividers, current sense, aux supply, SPIN header
A10: Connectors + test points | B10: 18 | C10: M | D10: Battery (35 A) + 400 V link + TPs
A11: Isolation barrier / creepage gap | B11: 20 | C11: M | D11: 400 V <-> battery separation under/around transformer
A12: Routing / margin | B12: 35 | C12: L | D12: Spacing, vias, keep-outs, single-sided routing overhead
A13: TOTAL allocated | B13: =SUM(B6:B12) -> 160
A14: Spare vs 196 cm^2 | B14: =B3-B13 -> 36
A16: Verdict: fits the 70x280 mm footprint with modest margin (conf M). Z-height is set by the RM12
A17: core (~25 mm) plus the top-side heatsink, so the module depth - not PCB area - is the tighter constraint.

Sheet Risk_Register
A1: Risk Register
A2: Likelihood (L) & Impact (I) on 1-5 scale; Score = L x I. Higher = attend first.
A4: ID | B4: Category | C4: Risk | D4: L | E4: I | F4: Score | G4: Mitigation | H4: Status
A5: M-01 | B5: Magnetics | C5: Leakage-only series L (~5% of magnetizing, single-turn primary) hard to hit AND control; sets power transfer | D5: 4 | E5: 4 | F5: =D5*E5 -> 16 | G5: Design winding separation for target leakage; measure & tune on prototype; keep discrete shim inductor as fallback | H5: Open
A6: T-01 | B6: Thermal/Device | C6: LV switch current at 23.8 V full-power corner (~42 A) vs 53 A rating -> comfortable margin; thermal still to manage | D6: 2 | E6: 3 | F6: =D6*E6 -> 6 | G6: Top-side heatsink + conduction; verify 1 MHz thermal derating at worst corner | H6: Open
A7: S-01 | B7: Sourcing | C7: GaN power ICs not on LCSC (EPC23102) / LMG2652 12-wk lead -> not fully PCBway-assemblable | D7: 4 | E7: 3 | F7: =D7*E7 -> 12 | G7: Dual-source; pre-order long-lead; all-LCSC Tokmas HV path; consign parts to PCBway | H7: Open
A8: L-01 | B8: Layout/EMI | C8: 1 MHz GaN gate loops, switching-node ringing, conducted/radiated EMI | D8: 4 | E8: 3 | F8: =D8*E8 -> 12 | G8: Tight power-loop layout; follow EPC/TI ref designs; slew-rate control; input/output filtering | H8: Open
A9: I-01 | B9: Isolation | C9: 400 V <-> battery isolation incl. sensing & gate-drive references and PCB creepage | D9: 3 | E9: 4 | F9: =D9*E9 -> 12 | G9: Define isolation standard; PCB creepage/clearance; isolated sense & bias across barrier | H9: Open
A10: C-01 | B10: Control | C10: Wide 2.47:1 battery range degrades ZVS range & raises RMS currents at SoC extremes | D10: 3 | E10: 3 | F10: =D10*E10 -> 9 | G10: Adaptive modulation (extended-phase-shift / triangular) in SPIN firmware; verify ZVS map | H10: Open
A11: E-01 | B11: Efficiency | C11: Meeting >95% at 1 MHz once real core, AC-copper, gate & ringing losses are included | D11: 3 | E11: 3 | F11: =D11*E11 -> 9 | G11: Refine loss model; optimise magnetics & ZVS; treat >95% as nominal-point target | H11: Open
A12: M-02 | B12: Magnetics | C12: Custom hand-wound transformer: cost, lead time and unit-to-unit repeatability | D12: 3 | E12: 3 | F12: =D12*E12 -> 9 | G12: Document winding spec; qualify a UK winder; characterise L_leak & losses per unit | H12: Open
A13: P-01 | B13: PCB | C13: 35 A on LV side: copper heating, via current, thermal coupling to devices | D13: 3 | E13: 3 | F13: =D13*E13 -> 9 | G13: 2 oz (or heavier) copper, large pours, paralleled layers, thermal vias | H13: Open
A14: R-01 | B14: Repairability | C14: GaN QFNs (incl. exposed-pad) are hard to hand-rework vs golden rules | D14: 2 | E14: 3 | F14: =D14*E14 -> 6 | G14: Single-sided placement; hot-air-reworkable layout; spacing; full test points | H14: Open
A15: X-01 | B15: Caps | C15: LV bus ripple-current rating at 1 MHz / high current | D15: 2 | E15: 3 | F15: =D15*E15 -> 6 | G15: Ceramic arrays with adequate ripple rating; verify thermals | H15: Open
A16: D-01 | B16: Control/Spec | C16: Bidirectional reference (analog OR serial) + 'no-error' logic complexity | D16: 2 | E16: 3 | F16: =D16*E16 -> 6 | G16: Leverage OwnTech SPIN stack; staged firmware bring-up; clear fault state machine | H16: Open

Sheet References
A1: References (all checkable)
A3: # | B3: Source | C3: Supports | D3: URL
A4: 1 | B4: TI LMG2100R026 product page | C4: LV GaN: 93 V cont/100 V pulsed, 53 A, 2.6 mΩ, integrated driver, top-cooled | D4: https://www.ti.com/product/LMG2100R026
A5: 2 | B5: TI LMG2100R026 datasheet (PDF) | C5: Electrical specs, 7.0x4.5 mm 18-VQFN, UVLO/clamp protection | D5: https://www.ti.com/lit/ds/symlink/lmg2100r026.pdf
A6: 3 | B6: DigiKey LMG2100R026VBNR | C6: Availability (in stock) & low-qty pricing - verify before order | D6: https://www.digikey.com/en/products/detail/texas-instruments/LMG2100R026VBNR/25811484
A7: 4 | B7: TI LMG2652 product page | C7: HV GaN: 650 V, 140 mΩ, integrated driver+sense, bottom-cooled | D7: https://www.ti.com/product/LMG2652
A8: 5 | B8: DigiKey LMG2652RFBR | C8: Availability / 12-week lead, 19-VQFN 8x6 mm | D8: https://www.digikey.com/en/products/detail/texas-instruments/LMG2652RFBR/26251057
A9: 6 | B9: LCSC CID12N65D (Tokmas) | C9: All-LCSC HV fallback, 650 V, from $0.6276 | D9: https://www.lcsc.com/product-detail/C21547657.html
A10: 7 | B10: Farnell B65815E0000R049 | C10: RM12 N49 core, UK source | D10: https://uk.farnell.com/epcos/b65815e0000r049/transformer-core-rm-n49-57mm/dp/4167325
A11: 8 | B11: TME B65815E0000R049 | C11: A_L 3700 nH, Ae 146 mm^2, sold as pair | D11: https://www.tme.eu/en/details/b65815e0000r049/ferrite-cores/epcos/
A12: 9 | B12: TDK RM12 datasheet | C12: A_L by grade (N49 = 3700 nH +30/-20%) | D12: https://www.tdk-electronics.tdk.com/inf/80/db/fer/rm_12.pdf
A13: 10 | B13: RM Cybernetics | C13: UK Litz wire (12 A / 3 A variants) | D13: https://www.rmcybernetics.com/
A14: 11 | B14: OwnTech SPIN | C14: Controller: STM32G4, HRTIM PWM, ADC 0-2.048 V | D14: https://www.owntech.org/spin-2/
A15: 12 | B15: OwnTech ADC docs | C15: ADC input range 0-2.048 V, PWM-triggered sampling | D15: https://docs.owntech.org/latest/examples/SPIN/ADC/adc_hrtim_trigger/
... A17: 14 | B17: PCBway online quote | C17: PCB fabrication cost calculator | D17: https://www.pcbway.com/orderonline.aspx
